pysbml4j/Configuration.py
pysbml4j/Network.py
pysbml4j/Sbml4j.py
pysbml4j/__init__.py
pysbml4j-1.3.1.dist-info/LICENSE
pysbml4j-1.3.1.dist-info/METADATA
pysbml4j-1.3.1.dist-info/WHEEL
pysbml4j-1.3.1.dist-info/top_level.txt
pysbml4j-1.3.1.dist-info/RECORD
