Metadata-Version: 2.1
Name: pysbml4j
Version: 1.3.1
Summary: The python client package to interact with a running SBML4j service instance
Home-page: https://github.com/kohlbacherlab/pysbml4j
Author: Thorsten Tiede
Author-email: thorsten.tiede@uni-tuebingen.de
Project-URL: Bug Tracker, https://github.com/kohlbacherlab/pysbml4j/issues
Classifier: Programming Language :: Python :: 3
Classifier: License :: OSI Approved :: MIT License
Classifier: Operating System :: OS Independent
Requires-Python: >=3.6
License-File: LICENSE
Requires-Dist: urllib3
